pyprotectorx/__init__.py
pyprotectorx/__main__.py
pyprotectorx/cli.py
pyprotectorx/core_311.py
pyprotectorx/core_312.py
pyprotectorx-5.1.0.dist-info/licenses/LICENSE
pyprotectorx-5.1.0.dist-info/METADATA
pyprotectorx-5.1.0.dist-info/WHEEL
pyprotectorx-5.1.0.dist-info/entry_points.txt
pyprotectorx-5.1.0.dist-info/top_level.txt
pyprotectorx-5.1.0.dist-info/RECORD
